fprime_ci/__init__.py
fprime_ci/__main__.py
fprime_ci/ci.py
fprime_ci/power.py
fprime_ci/utilities.py
fprime_ci/plugin/__init__.py
fprime_ci/plugin/definitions.py
fprime_ci/plugin/system.py
fprime_ci/plugins/__init__.py
fprime_ci/plugins/null.py
fprime_ci-0.0.1.dist-info/METADATA
fprime_ci-0.0.1.dist-info/WHEEL
fprime_ci-0.0.1.dist-info/entry_points.txt
fprime_ci-0.0.1.dist-info/top_level.txt
fprime_ci-0.0.1.dist-info/RECORD
